[{"id":1,"first_name":"Dina","last_name":"Keely","email":"dkeely0@omniture.com","gender":"Female","salary":9842},
{"id":2,"first_name":"Ursuline","last_name":"Tavner","email":"utavner1@smugmug.com","gender":"Female","salary":6450},
{"id":3,"first_name":"See","last_name":"Calterone","email":"scalterone2@yolasite.com","gender":"Male","salary":7229},
{"id":4,"first_name":"Gay","last_name":"Emmet","email":"gemmet3@surveymonkey.com","gender":"Female","salary":12135},
{"id":5,"first_name":"Deny","last_name":"Rampling","email":"drampling4@ow.ly","gender":"Female","salary":7252},
{"id":6,"first_name":"Clair","last_name":"Burnhard","email":"cburnhard5@icq.com","gender":"Male","salary":7373},
{"id":7,"first_name":"Germain","last_name":"Golder","email":"ggolder6@bravesites.com","gender":"Female","salary":11810},
{"id":8,"first_name":"Layla","last_name":"Jobes","email":"ljobes7@cmu.edu","gender":"Female","salary":14252},
{"id":9,"first_name":"Maximilien","last_name":"Chambers","email":"mchambers8@utexas.edu","gender":"Male","salary":7280},
{"id":10,"first_name":"Serge","last_name":"Mawne","email":"smawne9@blogs.com","gender":"Male","salary":11772},
{"id":11,"first_name":"Sandie","last_name":"Blowers","email":"sblowersa@tripadvisor.com","gender":"Female","salary":7176},
{"id":12,"first_name":"Esdras","last_name":"Althrope","email":"ealthropeb@sakura.ne.jp","gender":"Male","salary":5670},
{"id":13,"first_name":"Kylie","last_name":"Pargiter","email":"kpargiterc@blogs.com","gender":"Female","salary":9821},
{"id":14,"first_name":"Christy","last_name":"Guerrin","email":"cguerrind@hatena.ne.jp","gender":"Female","salary":13094},
{"id":15,"first_name":"Trescha","last_name":"Phillpot","email":"tphillpote@imgur.com","gender":"Female","salary":8516},
{"id":16,"first_name":"Oralee","last_name":"Affron","email":"oaffronf@instagram.com","gender":"Female","salary":4634},
{"id":17,"first_name":"Shannon","last_name":"Ren","email":"sreng@technorati.com","gender":"Male","salary":9869},
{"id":18,"first_name":"Ferd","last_name":"Craufurd","email":"fcraufurdh@shutterfly.com","gender":"Male","salary":4665},
{"id":19,"first_name":"Abigael","last_name":"McSwan","email":"amcswani@cbslocal.com","gender":"Female","salary":7190},
{"id":20,"first_name":"Emmi","last_name":"Farnin","email":"efarninj@alibaba.com","gender":"Female","salary":5294}]